isityaml/__init__.py
isityaml/urls.py
isityaml/views.py
isityaml/templates/isityaml/isityaml.html
isityaml-0.7.dist-info/LICENSE.txt
isityaml-0.7.dist-info/METADATA
isityaml-0.7.dist-info/WHEEL
isityaml-0.7.dist-info/top_level.txt
isityaml-0.7.dist-info/RECORD
