Metadata-Version: 2.1
Name: isityaml
Version: 0.7
Summary: A Django app for checking the correctness of YAML
Home-page: http://pypi.python.org/pypi/isityaml/
Author: Peter Murphy
Author-email: peterkmurphy@gmail.com
License: LICENSE.txt
Keywords: YAML parse text Django
Platform: UNKNOWN
Classifier: Development Status :: 4 - Beta
Classifier: Environment :: Other Environment
Classifier: Environment :: Web Environment
Classifier: Intended Audience :: Developers
Classifier: Intended Audience :: Education
Classifier: Intended Audience :: End Users/Desktop
Classifier: Intended Audience :: Other Audience
Classifier: License :: OSI Approved :: BSD License
Classifier: Programming Language :: Python
Classifier: Programming Language :: Python :: 2
Classifier: Development Status :: 4 - Beta
Classifier: License :: OSI Approved :: BSD License
Classifier: Operating System :: OS Independent
Classifier: Operating System :: MacOS
Classifier: Operating System :: Microsoft :: Windows
Classifier: Operating System :: POSIX
Classifier: Topic :: Education
Requires-Dist: Django (>=1.1.1)
Requires-Dist: PyYAML (>=3.0)
